MANIFEST.in
setup.cfg
setup.py
eadator/__init__.py
eadator/eadator.py
eadator.egg-info/PKG-INFO
eadator.egg-info/SOURCES.txt
eadator.egg-info/dependency_links.txt
eadator.egg-info/entry_points.txt
eadator.egg-info/not-zip-safe
eadator.egg-info/requires.txt
eadator.egg-info/top_level.txt
eadator/ents/ead.dtd
eadator/ents/ead.xsd
eadator/ents/eadcatalog.xml
eadator/ents/index.html
eadator/ents/iso-cyr1.ent
eadator/ents/iso-cyr2.ent
eadator/ents/iso-dia.ent
eadator/ents/iso-grk1.ent
eadator/ents/iso-grk2.ent
eadator/ents/iso-grk3.ent
eadator/ents/iso-grk4.ent
eadator/ents/iso-lat1.ent
eadator/ents/iso-lat2.ent
eadator/ents/iso-num.ent
eadator/ents/iso-pub.ent
eadator/ents/iso-tech.ent
eadator/ents/xlink.xsd
eadator/ents/related_optional/index.html
eadator/ents/related_optional/eadlocal/eadlocal.ent
eadator/ents/related_optional/eadlocal/index.html
eadator/ents/related_optional/sgml/eadsgml.dcl
eadator/ents/related_optional/sgml/index.html
eadator/ents/related_optional/xml/eadcatalog.xml
eadator/ents/related_optional/xml/index.html
eadator/ents/related_optional/xml/charentities/index.html
eadator/ents/related_optional/xml/charentities/iso-cyr1.ent
eadator/ents/related_optional/xml/charentities/iso-cyr2.ent
eadator/ents/related_optional/xml/charentities/iso-dia.ent
eadator/ents/related_optional/xml/charentities/iso-grk1.ent
eadator/ents/related_optional/xml/charentities/iso-grk2.ent
eadator/ents/related_optional/xml/charentities/iso-grk3.ent
eadator/ents/related_optional/xml/charentities/iso-grk4.ent
eadator/ents/related_optional/xml/charentities/iso-lat1.ent
eadator/ents/related_optional/xml/charentities/iso-lat2.ent
eadator/ents/related_optional/xml/charentities/iso-num.ent
eadator/ents/related_optional/xml/charentities/iso-pub.ent
eadator/ents/related_optional/xml/charentities/iso-tech.ent
tests/__init__.py
tests/test_eadator.py