Metadata-Version: 1.1
Name: eadator
Version: 0.3.4
Summary: EAD2002 (DTD or XSD) universal validator
Home-page: https://github.com/eadhost/eadator
Author: Brian Tingle
Author-email: brian.tingle.cdlib.org@gmail.com
License: BSD
Download-URL: https://github.com/eadhost/eadator/tarball/0.3.4
Keywords: validate ead 2002 xml xsd dtd
Platform: UNKNOWN
